TFEA/__init__.py
TFEA/__main__.py
TFEA/annotate_motifs.py
TFEA/bedgraph_intersect.py
TFEA/combine.py
TFEA/config.py
TFEA/enrichment.py
TFEA/exceptions.py
TFEA/main.py
TFEA/main.sbatch
TFEA/multiprocess.py
TFEA/mumerge.py
TFEA/mumerge_test_unit.py
TFEA/output.py
TFEA/plot.py
TFEA/process_inputs.py
TFEA/rank.py
TFEA/scanner.py
TFEA/simulate/__init__.py
TFEA/simulate/__main__.py
TFEA/simulate/main.py
TFEA/simulate/motif_insert.py
TFEA/simulate/pull_sequences.py
TFEA/simulate/simulate.sbatch
TFEA/test/__init__.py
TFEA/test/test.sbatch
TFEA/test/test_full.py
TFEA/test/test_install.py
TFEA/test/test_simulate.py
TFEA/test/test_files/Allen2014_simulated_10.fa
TFEA/test/test_files/SRR1105736.sorted.chr22.subsample.bam
TFEA/test/test_files/SRR1105736.sorted.chr22.subsample.bam.bai
TFEA/test/test_files/SRR1105736.tfit_bidirs.chr22.bed
TFEA/test/test_files/SRR1105737.sorted.chr22.subsample.bam
TFEA/test/test_files/SRR1105737.sorted.chr22.subsample.bam.bai
TFEA/test/test_files/SRR1105737.tfit_bidirs.chr22.bed
TFEA/test/test_files/SRR1105738.sorted.chr22.subsample.bam
TFEA/test/test_files/SRR1105738.sorted.chr22.subsample.bam.bai
TFEA/test/test_files/SRR1105738.tfit_bidirs.chr22.bed
TFEA/test/test_files/SRR1105739.sorted.chr22.subsample.bam
TFEA/test/test_files/SRR1105739.sorted.chr22.subsample.bam.bai
TFEA/test/test_files/SRR1105739.tfit_bidirs.chr22.bed
TFEA/test/test_files/chr22.fa
TFEA/test/test_files/chr22.fa.fai
TFEA/test/test_files/count_file.header.bed
TFEA/test/test_files/deseq_test.R
TFEA/test/test_files/test_combined_file.bed
TFEA/test/test_files/test_config.ini
TFEA/test/test_files/test_database.meme
TFEA/test/test_files/test_database2.meme
TFEA/test/test_files/test_fasta_file.fa
TFEA/test/test_files/test_motif_annotation.bed
TFEA/test/test_files/test_ranked_file.bed
tfea-1.1.4.data/scripts/TFEA
tfea-1.1.4.data/scripts/TFEA-annotate
tfea-1.1.4.data/scripts/TFEA-simulate
tfea-1.1.4.dist-info/LICENSE
tfea-1.1.4.dist-info/METADATA
tfea-1.1.4.dist-info/WHEEL
tfea-1.1.4.dist-info/top_level.txt
tfea-1.1.4.dist-info/RECORD
