Metadata-Version: 2.1
Name: tfea
Version: 1.1.4
Summary: Transcription Factor Enrichment Analysis
Home-page: https://github.com/Dowell-Lab/TFEA.git
Author: Jonathan Rubin
Author-email: jonathan.rubin@colorado.edu
License: GPL-3.0
Platform: UNKNOWN
Requires-Python: >=3
Requires-Dist: matplotlib (>=3.1.1)
Requires-Dist: scipy
Requires-Dist: numpy
Requires-Dist: pybedtools
Requires-Dist: htseq
Requires-Dist: psutil
Requires-Dist: ujson
Requires-Dist: pysam (==0.15.2)
